elemental_analysis_tools/__init__.py
elemental_analysis_tools/blankCorrection.py
elemental_analysis_tools/elementarDensity.py
elemental_analysis_tools/fitResponseFactor.py
elemental_analysis_tools/micromatter.py
elemental_analysis_tools/responseFactor.py
elemental_analysis_tools/shimadzu.py
elemental_analysis_tools/utils.py
elemental_analysis_tools/winqxas.py
tests/__init__.py
tests/test_blankCorrection.py
tests/test_elementarDensity.py
tests/test_fitResponseFactor.py
tests/test_micromatter.py
tests/test_responseFactor.py
tests/test_shimadzu.py
tests/test_winqxas.py
elemental_analysis_tools-0.0.4.dist-info/LICENSE
elemental_analysis_tools-0.0.4.dist-info/METADATA
elemental_analysis_tools-0.0.4.dist-info/WHEEL
elemental_analysis_tools-0.0.4.dist-info/top_level.txt
elemental_analysis_tools-0.0.4.dist-info/RECORD
