Metadata-Version: 2.1
Name: elemental-analysis-tools
Version: 0.0.4
Summary: elemental_analysis_tools package
Home-page: https://github.com/elemental-analysis-group/elemental_analysis_tools.git
Author: Thiago Gomes Veríssimo
Author-email: verissimotgv@gmail.com
License: UNKNOWN
Platform: UNKNOWN
Requires-Dist: pyxray (>=1.3)
Requires-Dist: numpy (>=1.14.1)
